fimf/__init__.py
fimf/core.py
fimf/fimf.css
fimf/release.py
fimf/script.py
fimf-0.2.0.dist-info/LICENSE
fimf-0.2.0.dist-info/METADATA
fimf-0.2.0.dist-info/WHEEL
fimf-0.2.0.dist-info/entry_points.txt
fimf-0.2.0.dist-info/top_level.txt
fimf-0.2.0.dist-info/RECORD
