Metadata-Version: 2.1
Name: fimf
Version: 0.2.0
Summary: command line (TUI) tool to find (and replace) patterns in multiple files
Author-email: Carsten Knoll <firstname.lastname@posteo.org>
License: GNU General Public License v3 (GPLv3)
Project-URL: Homepage, https://github.com/cknoll/fimf
Classifier: Development Status :: 3 - Alpha
Classifier: Intended Audience :: Developers
Classifier: Programming Language :: Python :: 3
Requires-Python: >=3.8
License-File: LICENSE
Requires-Dist: ipydex
Requires-Dist: textual
